squareofnumber/__init__.py
squareofnumber/square.py
sqaureofnumber-0.0.4.dist-info/LICENSE
sqaureofnumber-0.0.4.dist-info/METADATA
sqaureofnumber-0.0.4.dist-info/WHEEL
sqaureofnumber-0.0.4.dist-info/top_level.txt
sqaureofnumber-0.0.4.dist-info/RECORD
